NYTimesArticleAPI/__init__.py
NYTimesArticleAPI/nytapi.py
NYTimesArticleAPI/search_api.py
NYTimesArticleAPI/tests.py
nytimesarticlev2/__init__.py
nytimesarticlev2/nytapi.py
nytimesarticlev2/search_api.py
nytimesarticlev2/tests.py
nytimesarticlev2-1.1.0.dist-info/LICENSE
nytimesarticlev2-1.1.0.dist-info/METADATA
nytimesarticlev2-1.1.0.dist-info/WHEEL
nytimesarticlev2-1.1.0.dist-info/top_level.txt
nytimesarticlev2-1.1.0.dist-info/zip-safe
nytimesarticlev2-1.1.0.dist-info/RECORD
